opendigger/__init__.py
opendigger/opendigger.py
opendigger-0.1.7.dist-info/LICENSE
opendigger-0.1.7.dist-info/METADATA
opendigger-0.1.7.dist-info/WHEEL
opendigger-0.1.7.dist-info/entry_points.txt
opendigger-0.1.7.dist-info/top_level.txt
opendigger-0.1.7.dist-info/RECORD
