Metadata-Version: 2.1
Name: opendigger
Version: 0.1.7
Summary: A CLI tool for fetching OpenDigger metrics
Home-page: https://github.com/TOMYUE/opendigger-cli
Author: TOMYUE
Author-email: tomyue2002@gmail.com
License: UNKNOWN
Platform: UNKNOWN
Classifier: Development Status :: 3 - Alpha
Classifier: Intended Audience :: Developers
Classifier: License :: OSI Approved :: MIT License
Classifier: Programming Language :: Python :: 3
Classifier: Programming Language :: Python :: 3.6
Classifier: Programming Language :: Python :: 3.7
Classifier: Programming Language :: Python :: 3.8
Classifier: Programming Language :: Python :: 3.9
License-File: LICENSE
Requires-Dist: numpy
Requires-Dist: plotext
Requires-Dist: matplotlib
